README.md
setup.cfg
setup.py
morph/__init__.py
morph/_models.py
morph/layers/__init__.py
morph/layers/sparse.py
morph/layers/widen.py
morph/nn/__init__.py
morph/nn/_morph_net.py
morph/nn/morph.py
morph/nn/shrink.py
morph/nn/utils.py
morph/nn/utils_test.py
morph/nn/widen.py
morph_py.egg-info/PKG-INFO
morph_py.egg-info/SOURCES.txt
morph_py.egg-info/dependency_links.txt
morph_py.egg-info/requires.txt
morph_py.egg-info/top_level.txt